napari_filament_annotator/__init__.py
napari_filament_annotator/_annotator.py
napari_filament_annotator/_params.py
napari_filament_annotator/_sample_data.py
napari_filament_annotator/_version.py
napari_filament_annotator/_widget.py
napari_filament_annotator/napari.yaml
napari_filament_annotator/_tests/__init__.py
napari_filament_annotator/_tests/conftest.py
napari_filament_annotator/_tests/test_annotator.py
napari_filament_annotator/_tests/test_geom.py
napari_filament_annotator/_tests/test_io.py
napari_filament_annotator/_tests/test_postproc.py
napari_filament_annotator/_tests/test_sample_data.py
napari_filament_annotator/utils/__init__.py
napari_filament_annotator/utils/const.py
napari_filament_annotator/utils/geom.py
napari_filament_annotator/utils/io.py
napari_filament_annotator/utils/postproc.py
napari_filament_annotator-0.1.2.dist-info/LICENSE
napari_filament_annotator-0.1.2.dist-info/METADATA
napari_filament_annotator-0.1.2.dist-info/WHEEL
napari_filament_annotator-0.1.2.dist-info/entry_points.txt
napari_filament_annotator-0.1.2.dist-info/top_level.txt
napari_filament_annotator-0.1.2.dist-info/RECORD
