Metadata-Version: 2.1
Name: napari-filament-annotator
Version: 0.1.2
Summary: Annotation of filaments / curvilinear structures in 3D
Home-page: https://github.com/amedyukhina/napari-filament-annotator
Author: Anna Medyukhina
Author-email: anna.medyukhina@gmail.com
License: Apache-2.0
Project-URL: Bug Tracker, https://github.com/amedyukhina/napari-filament-annotator/issues
Project-URL: Documentation, https://github.com/amedyukhina/napari-filament-annotator#README.md
Project-URL: Source Code, https://github.com/amedyukhina/napari-filament-annotator
Project-URL: User Support, https://github.com/amedyukhina/napari-filament-annotator/issues
Classifier: Development Status :: 3 - Alpha
Classifier: Framework :: napari
Classifier: Intended Audience :: Science/Research
Classifier: License :: OSI Approved :: Apache Software License
Classifier: Operating System :: OS Independent
Classifier: Programming Language :: Python
Classifier: Programming Language :: Python :: 3
Classifier: Programming Language :: Python :: 3 :: Only
Classifier: Programming Language :: Python :: 3.8
Classifier: Programming Language :: Python :: 3.9
Classifier: Programming Language :: Python :: 3.10
Classifier: Topic :: Scientific/Engineering :: Image Processing
Requires-Python: >=3.8
License-File: LICENSE
Requires-Dist: Geometry3D
Requires-Dist: networkx
Requires-Dist: numpy
Requires-Dist: magicgui
Requires-Dist: pandas
Requires-Dist: qtpy
Requires-Dist: scipy
Requires-Dist: sklearn
Requires-Dist: imageio (!=2.22.1)
Provides-Extra: testing
Requires-Dist: tox ; extra == 'testing'
Requires-Dist: pytest ; extra == 'testing'
Requires-Dist: pytest-cov ; extra == 'testing'
Requires-Dist: pytest-qt ; extra == 'testing'
Requires-Dist: napari ; extra == 'testing'
Requires-Dist: pyqt5 ; extra == 'testing'
